{"stats":{"minecraft:used":{"twilightforest:diamond_minotaur_axe":5,"minecraft:lava_bucket":1,"iceandfire:dragon_horn":1,"minecraft:blackstone":1,"iceandfire:dragonsteel_ice_sword":123,"evilcraft:purifier":1,"minecraft:torch":4,"minecraft:dirt":1,"minecraft:golden_carrot":8,"iceandfire:dragonsteel_ice_pickaxe":23,"minecraft:carrot":23,"minecraft:bucket":1,"iceandfire:dragonegg_blue":2,"minecraft:splash_potion":3,"minecraft:milk_bucket":1},"minecraft:killed":{"minecraft:skeleton":17,"minecraft:cave_spider":4,"enemyexpansion:huntsman":1,"minecraft:spider":6,"iceandfire:ice_dragon":1,"minecraft:wither_skeleton":29},"minecraft:picked_up":{"iceandfire:dragonbone":29,"evilcraft:exalted_crafter":1,"iceandfire:witherbone":5,"minecraft:torch":2,"nordic_structures:tyrfingr":1,"minecraft:enchanted_book":1,"minecraft:carrot":81,"iceandfire:dragonscales_blue":83,"minecraft:string":7,"minecraft:dirt":2,"iceandfire:dragon_skull_ice":1,"minecraft:bone":64,"minecraft:arrow":50,"dungeonnowloading:spawner_fragment":56,"minecraft:blackstone":2,"minecraft:spruce_planks":1,"iceandfire:dragonegg_blue":1,"minecraft:rose_bush":1,"iceandfire:ice_dragon_flesh":9,"minecraft:mossy_cobblestone_stairs":1,"minecraft:smooth_quartz":2,"minecraft:coal":27,"iceandfire:ice_dragon_heart":1},"minecraft:crafted":{"minecraft:golden_carrot":40,"minecraft:torch":52},"minecraft:custom":{"minecraft:time_since_rest":26664,"minecraft:sprint_one_cm":95865,"minecraft:damage_taken":648,"minecraft:walk_one_cm":101391,"minecraft:interact_with_anvil":17,"minecraft:mob_kills":58,"minecraft:drop":45,"minecraft:damage_dealt":18094,"minecraft:player_kills":1,"minecraft:interact_with_crafting_table":1,"minecraft:fly_one_cm":196119,"minecraft:open_barrel":1,"minecraft:open_chest":44,"minecraft:crouch_one_cm":301,"minecraft:play_time":70499,"minecraft:sneak_time":561,"minecraft:damage_dealt_resisted":8122,"minecraft:jump":385,"minecraft:time_since_death":70499,"minecraft:walk_on_water_one_cm":122,"minecraft:sleep_in_bed":1,"minecraft:climb_one_cm":2428,"minecraft:total_world_time":70499,"minecraft:fall_one_cm":8296},"minecraft:dropped":{"minecraft:enchanted_book":1,"minecraft:spruce_planks":1,"iceandfire:dragon_meal":41,"evilcraft:exalted_crafter":1,"dungeonnowloading:spawner_fragment":2},"minecraft:mined":{"minecraft:carrots":21,"minecraft:mossy_cobblestone_stairs":1,"minecraft:blackstone":2,"minecraft:torch":2,"minecraft:spruce_fence":5,"minecraft:grass_block":1,"minecraft:rose_bush":1,"minecraft:cobweb":3,"minecraft:cyan_carpet":1,"minecraft:smooth_quartz":2,"minecraft:dirt":1,"minecraft:packed_ice":11,"minecraft:spawner":17}},"DataVersion":3465}